telegram_group_bot/__init__.py
telegram_group_bot/bot.py
telegram_group_bot/cli.py
telegram_group_bot/config.py
telegram_group_bot-0.1.3.dist-info/METADATA
telegram_group_bot-0.1.3.dist-info/WHEEL
telegram_group_bot-0.1.3.dist-info/entry_points.txt
telegram_group_bot-0.1.3.dist-info/top_level.txt
telegram_group_bot-0.1.3.dist-info/RECORD
