Metadata-Version: 2.1
Name: telegram-group-bot
Version: 0.1.3
Summary: UNKNOWN
Home-page: UNKNOWN
License: UNKNOWN
Platform: UNKNOWN
Requires-Python: >=3.9
Requires-Dist: python-telegram-bot (==13.1)
Requires-Dist: pydantic (==1.7.3)
Requires-Dist: click (==7.1.2)
Requires-Dist: toml (==0.10.2)
Provides-Extra: dev
Requires-Dist: pytest (==6.1.2) ; extra == 'dev'
Requires-Dist: pytest-xdist (==2.1.0) ; extra == 'dev'
Requires-Dist: pre-commit (==2.9.2) ; extra == 'dev'
Requires-Dist: wheel (==0.36.0) ; extra == 'dev'
Requires-Dist: twine (==3.2.0) ; extra == 'dev'
